hierarchical/HierarchicalDict.py
hierarchical/__init__.py
hierarchical-0.0.9.dist-info/DESCRIPTION.rst
hierarchical-0.0.9.dist-info/METADATA
hierarchical-0.0.9.dist-info/RECORD
hierarchical-0.0.9.dist-info/WHEEL
hierarchical-0.0.9.dist-info/metadata.json
hierarchical-0.0.9.dist-info/top_level.txt
