Metadata-Version: 2.0
Name: hierarchical
Version: 0.0.9
Summary: Hierarchical interface to Python dictionaries
Home-page: https://github.com/locuslab/hierarchical
Author: Eric Wong
Author-email: ericwong@cs.cmu.edu
License: Apache 2.0
Platform: any
